LICENSE
MANIFEST.in
README.md
requirements.txt
setup.py
../LICENSE
pyauto/__init__.py
pyauto.core.egg-info/PKG-INFO
pyauto.core.egg-info/SOURCES.txt
pyauto.core.egg-info/dependency_links.txt
pyauto.core.egg-info/requires.txt
pyauto.core.egg-info/top_level.txt
pyauto/core/__init__.py
pyauto/core/config.py
pyauto/core/deploy.py
pyauto/core/taskgen.py
pyauto/core/tasks.py
pyauto/core/template.py