Metadata-Version: 1.0
Name: pyauto.core
Version: 0.1.2
Summary: PyAuto Core
Home-page: https://github.com/adamjaso/pyauto/tree/master/core
Author: Adam Jaso
Author-email: UNKNOWN
License:                     GNU GENERAL PUBLIC LICENSE
